smartutils/__init__.py
smartutils/timeutil.py
smartutils-1.0.3.dist-info/METADATA
smartutils-1.0.3.dist-info/WHEEL
smartutils-1.0.3.dist-info/top_level.txt
smartutils-1.0.3.dist-info/RECORD
