Metadata-Version: 2.1
Name: smartutils
Version: 1.0.3
Summary: Smart collection of utilities for your code
Home-page: UNKNOWN
Author: Arockia Arulnathan
Author-email: arockia@scriptinghub.com
License: UNKNOWN
Platform: UNKNOWN
Classifier: Programming Language :: Python :: 3
Classifier: License :: OSI Approved :: MIT License
Classifier: Operating System :: OS Independent
Requires-Python: >=3.6
